negf/__init__.py
negf/itgf.py
negf/scgf.py
negf/.idea/.gitignore
negf/.idea/.name
negf/.idea/echocjl.iml
negf/.idea/misc.xml
negf/.idea/modules.xml
negf/.idea/workspace.xml
negf/.idea/inspectionProfiles/profiles_settings.xml
negf-0.0.1.dist-info/METADATA
negf-0.0.1.dist-info/WHEEL
negf-0.0.1.dist-info/RECORD
