Metadata-Version: 2.1
Name: negf
Version: 0.0.1
Summary: A tool for calculating the quantum transport properties of condensed matter systems based on the principle of non-equilibrium Green's functions
Project-URL: Homepage, https://github.com/xiaoshengweixiang/negf
Project-URL: Bug Tracker, https://github.com/xiaoshengweixiang/negf/issues
Author-email: Jinli Chen <1900011342@pku.edu.cn>
Classifier: License :: OSI Approved :: MIT License
Classifier: Operating System :: OS Independent
Classifier: Programming Language :: Python :: 3
Requires-Python: >=3.7
